openqaoa_azure/__init__.py
openqaoa_azure/_version.py
openqaoa_azure/backend_config.py
openqaoa_azure/backends/__init__.py
openqaoa_azure/backends/devices.py
openqaoa_azure-0.2.6.dist-info/LICENSE
openqaoa_azure-0.2.6.dist-info/METADATA
openqaoa_azure-0.2.6.dist-info/WHEEL
openqaoa_azure-0.2.6.dist-info/entry_points.txt
openqaoa_azure-0.2.6.dist-info/top_level.txt
openqaoa_azure-0.2.6.dist-info/RECORD
