Metadata-Version: 2.1
Name: openqaoa-azure
Version: 0.2.6
Summary: Azure Plug-in for OpenQAOA
Home-page: https://github.com/entropicalabs/openqaoa
Author: Entropica Labs
License: MIT
Keywords: quantum optimisation SDK
Classifier: Programming Language :: Python :: 3.8
Classifier: Programming Language :: Python :: 3.9
Classifier: Programming Language :: Python :: 3.10
Classifier: Operating System :: OS Independent
Requires-Python: >=3.8, <3.11
License-File: LICENSE
Requires-Dist: openqaoa-core ==0.2.6
Requires-Dist: openqaoa-qiskit ==0.2.6
Requires-Dist: qdk
Requires-Dist: qiskit-qir
Requires-Dist: qiskit-ionq
Requires-Dist: azure-quantum[qiskit]
